{
  "attributes": [
    {
      "default": "nil",
      "size": null,
      "type": "bigint",
      "source": "id",
      "references": null,
      "allow_nil?": false,
      "generated?": true,
      "primary_key?": true
    },
    {
      "default": "nil",
      "size": null,
      "type": "text",
      "source": "name",
      "references": null,
      "allow_nil?": false,
      "generated?": false,
      "primary_key?": false
    },
    {
      "default": "nil",
      "size": null,
      "type": "text",
      "source": "subject",
      "references": null,
      "allow_nil?": false,
      "generated?": false,
      "primary_key?": false
    },
    {
      "default": "nil",
      "size": null,
      "type": "text",
      "source": "text_body",
      "references": null,
      "allow_nil?": false,
      "generated?": false,
      "primary_key?": false
    },
    {
      "default": "nil",
      "size": null,
      "type": "text",
      "source": "html_body",
      "references": null,
      "allow_nil?": false,
      "generated?": false,
      "primary_key?": false
    },
    {
      "default": "fragment(\"now()\")",
      "size": null,
      "type": "utc_datetime_usec",
      "source": "created_at",
      "references": null,
      "allow_nil?": false,
      "generated?": false,
      "primary_key?": false
    },
    {
      "default": "fragment(\"now()\")",
      "size": null,
      "type": "utc_datetime_usec",
      "source": "updated_at",
      "references": null,
      "allow_nil?": false,
      "generated?": false,
      "primary_key?": false
    }
  ],
  "table": "templates",
  "hash": "CF48630B2AE08DF04E1E64817CED8D7AB073768CEAF3ECCF801EB8808979A255",
  "repo": "Elixir.Vachan.Repo",
  "identities": [],
  "schema": null,
  "multitenancy": {
    "global": null,
    "strategy": null,
    "attribute": null
  },
  "base_filter": null,
  "check_constraints": [],
  "custom_indexes": [],
  "custom_statements": [],
  "has_create_action": true
}